MANIFEST.in
README.md
setup.py
bpy_lambda/__init__.py
bpy_lambda/__init__.pyc
bpy_lambda/bpy.so
bpy_lambda/libGLU.so.1
bpy_lambda/libHalf.so.12
bpy_lambda/libIex.so.12
bpy_lambda/libIlmImf.so.22
bpy_lambda/libIlmThread.so.12
bpy_lambda/libImath.so.12
bpy_lambda/libOpenImageIO.so.1.7
bpy_lambda/libboost_filesystem.so.1.60.0
bpy_lambda/libboost_regex.so.1.60.0
bpy_lambda/libboost_system.so.1.60.0
bpy_lambda/libboost_thread.so.1.60.0
bpy_lambda/libopenjpeg.so.2
bpy_lambda/libpython3.6m.so.1.0
bpy_lambda.egg-info/PKG-INFO
bpy_lambda.egg-info/SOURCES.txt
bpy_lambda.egg-info/dependency_links.txt
bpy_lambda.egg-info/top_level.txt
bpy_lambda/2.79/scripts/addons/add_curve_ivygen.py
bpy_lambda/2.79/scripts/addons/animation_add_corrective_shape_key.py
bpy_lambda/2.79/scripts/addons/animation_animall.py
bpy_lambda/2.79/scripts/addons/bone_selection_sets.py
bpy_lambda/2.79/scripts/addons/camera_turnaround.py
bpy_lambda/2.79/scripts/addons/curve_assign_shapekey.py
bpy_lambda/2.79/scripts/addons/curve_simplify.py
bpy_lambda/2.79/scripts/addons/depsgraph_debug.py
bpy_lambda/2.79/scripts/addons/development_edit_operator.py
bpy_lambda/2.79/scripts/addons/development_icon_get.py
bpy_lambda/2.79/scripts/addons/development_iskeyfree.py
bpy_lambda/2.79/scripts/addons/io_anim_camera.py
bpy_lambda/2.79/scripts/addons/io_export_paper_model.py
bpy_lambda/2.79/scripts/addons/io_export_pc2.py
bpy_lambda/2.79/scripts/addons/io_import_images_as_planes.py
bpy_lambda/2.79/scripts/addons/lighting_dynamic_sky.py
bpy_lambda/2.79/scripts/addons/lighting_tri_lights.py
bpy_lambda/2.79/scripts/addons/mesh_auto_mirror.py
bpy_lambda/2.79/scripts/addons/mesh_bsurfaces.py
bpy_lambda/2.79/scripts/addons/mesh_f2.py
bpy_lambda/2.79/scripts/addons/mesh_looptools.py
bpy_lambda/2.79/scripts/addons/node_arrange.py
bpy_lambda/2.79/scripts/addons/node_presets.py
bpy_lambda/2.79/scripts/addons/node_wrangler.py
bpy_lambda/2.79/scripts/addons/object_boolean_tools.py
bpy_lambda/2.79/scripts/addons/object_color_rules.py
bpy_lambda/2.79/scripts/addons/object_edit_linked.py
bpy_lambda/2.79/scripts/addons/object_skinify.py
