Metadata-Version: 1.0
Name: bpy-lambda
Version: 1.3.1
Summary: A compiled binary of Blender-as-a-Python-Module (bpy) for use in AWS Lambda
Home-page: https://github.com/bcongdon/bpy_lambda
Author: Benjamin Congdon
Author-email: me@bcon.gdn
License: UNKNOWN
Platform: UNKNOWN
